cryotrans/__init__.py
cryotrans/gridding.py
cryotrans/ode_net.py
cryotrans/particles.py
cryotrans/predict.py
cryotrans/tetramesh.py
cryotrans/train.py
cryotrans/utility.py
cryotrans/velocity_net.py
cryotrans/wasserstein2_loss.py
cryotrans-1.0.0.dist-info/AUTHORS
cryotrans-1.0.0.dist-info/LICENSE
cryotrans-1.0.0.dist-info/METADATA
cryotrans-1.0.0.dist-info/WHEEL
cryotrans-1.0.0.dist-info/entry_points.txt
cryotrans-1.0.0.dist-info/top_level.txt
cryotrans-1.0.0.dist-info/RECORD
