Metadata-Version: 2.1
Name: cryotrans
Version: 1.0.0
Summary: CryoTRANS: Predicting high-resolution maps of rare conformations using neural ODEs in cryo-EM
Author-email: Xiao Fan <fanx20@mails.tsinghua.edu.cn>, Qi Zhang <q-zhang20@mails.tsinghua.edu.cn>, Hui Zhang <zhanghui23@mails.tsinghua.edu.cn>, Jianying Zhu <zhu-jy20@mails.tsinghua.edu.cn>, Lili Ju <ju@math.sc.edu>, Zuoqiang Shi <qshi@mail.tsinghua.edu.cn>, Mingxu Hu <humingxu@smart.org.cn>, Chenglong Bao <clbao@mail.tsinghua.edu.cn>
License: GNU GENERAL PUBLIC LICENSE
Project-URL: Homepage, https://github.com/mxhulab/cryotrans
Classifier: Programming Language :: Python :: 3
Classifier: License :: OSI Approved :: GNU General Public License v3 (GPLv3)
Classifier: Operating System :: OS Independent
Classifier: Environment :: GPU :: NVIDIA CUDA
Classifier: Topic :: Scientific/Engineering :: Image Processing
Requires-Python: >=3.7
License-File: LICENSE
License-File: AUTHORS
Requires-Dist: numpy >=1.18
Requires-Dist: mrcfile >=1.4.3
Requires-Dist: cupy >=10
Requires-Dist: torch >=1.10
